odoo/addons/stock_request_cancel_confirm/README.rst
odoo/addons/stock_request_cancel_confirm/__init__.py
odoo/addons/stock_request_cancel_confirm/__manifest__.py
odoo/addons/stock_request_cancel_confirm/i18n/stock_request_cancel_confirm.pot
odoo/addons/stock_request_cancel_confirm/model/__init__.py
odoo/addons/stock_request_cancel_confirm/model/stock_request.py
odoo/addons/stock_request_cancel_confirm/model/stock_request_order.py
odoo/addons/stock_request_cancel_confirm/readme/CONTRIBUTORS.rst
odoo/addons/stock_request_cancel_confirm/readme/DESCRIPTION.rst
odoo/addons/stock_request_cancel_confirm/static/description/icon.png
odoo/addons/stock_request_cancel_confirm/static/description/index.html
odoo14_addon_stock_request_cancel_confirm-14.0.1.0.1.dist-info/METADATA
odoo14_addon_stock_request_cancel_confirm-14.0.1.0.1.dist-info/WHEEL
odoo14_addon_stock_request_cancel_confirm-14.0.1.0.1.dist-info/top_level.txt
odoo14_addon_stock_request_cancel_confirm-14.0.1.0.1.dist-info/RECORD
